edwardsserial/__init__.py
edwardsserial/descriptors.py
edwardsserial/nEXT.py
edwardsserial/serial_protocol.py
edwardsserial/tic/__init__.py
edwardsserial/tic/gauge.py
edwardsserial/tic/pump.py
edwardsserial/tic/tic.py
edwardsserial-0.3.3.dist-info/LICENSE
edwardsserial-0.3.3.dist-info/WHEEL
edwardsserial-0.3.3.dist-info/METADATA
edwardsserial-0.3.3.dist-info/RECORD
