Metadata-Version: 2.1
Name: edwardsserial
Version: 0.3.3
Summary: Python API implementing the serial protocoll from edwards vacuum.
Home-page: https://gitlab.com/codingcoffeebean/edwardsserial
License: MIT
Keywords: TIC,edwards,vacuum
Author: codingcoffeebean
Author-email: contact@codingcoffeebean.com
Requires-Python: >=3.7.2,<4.0.0
Classifier: License :: OSI Approved :: MIT License
Classifier: Programming Language :: Python :: 3
Classifier: Programming Language :: Python :: 3.10
Classifier: Programming Language :: Python :: 3.8
Classifier: Programming Language :: Python :: 3.9
Requires-Dist: pyserial (>2.5.0)
Project-URL: Documentation, https://codingcoffeebean.gitlab.io/edwardsserial/
Project-URL: Repository, https://gitlab.com/codingcoffeebean/edwardsserial
